refine_contigs/__init__.py
refine_contigs/__main__.py
refine_contigs/_version.py
refine_contigs/merge.py
refine_contigs/split.py
refine_contigs/utils.py
refine_contigs-1.0.4.data/scripts/minimus2_mod
refine_contigs-1.0.4.dist-info/LICENSE
refine_contigs-1.0.4.dist-info/METADATA
refine_contigs-1.0.4.dist-info/WHEEL
refine_contigs-1.0.4.dist-info/entry_points.txt
refine_contigs-1.0.4.dist-info/top_level.txt
refine_contigs-1.0.4.dist-info/RECORD
